iCEburn/__init__.py
iCEburn/__main__.py
iCEburn/libiceblink.py
iCEburn/regtool.py
iCEburn-0.1.1.dist-info/METADATA
iCEburn-0.1.1.dist-info/RECORD
iCEburn-0.1.1.dist-info/WHEEL
iCEburn-0.1.1.dist-info/entry_points.txt
iCEburn-0.1.1.dist-info/top_level.txt
