Metadata-Version: 2.1
Name: iCEburn
Version: 0.1.1
Summary: Programmer for iCEblink40 boards
Home-page: https://github.com/davidcarne/iceBurn
Author: David Carne
Author-email: davidcarne@gmail.com
License: BSD
Keywords: fpga,ice40,programmer
Platform: UNKNOWN
Classifier: License :: OSI Approved :: BSD License
Classifier: Programming Language :: Python :: 3.0
Classifier: Operating System :: OS Independent
Requires-Python: >3.3
Requires-Dist: pyusb
